odoo/addons/stock_move_line_multi_company_security/README.rst
odoo/addons/stock_move_line_multi_company_security/__init__.py
odoo/addons/stock_move_line_multi_company_security/__manifest__.py
odoo/addons/stock_move_line_multi_company_security/i18n/stock_move_line_multi_company_security.pot
odoo/addons/stock_move_line_multi_company_security/models/__init__.py
odoo/addons/stock_move_line_multi_company_security/models/stock_move_line.py
odoo/addons/stock_move_line_multi_company_security/readme/CONTRIBUTORS.rst
odoo/addons/stock_move_line_multi_company_security/readme/DESCRIPTION.rst
odoo/addons/stock_move_line_multi_company_security/readme/INSTALL.rst
odoo/addons/stock_move_line_multi_company_security/readme/ROADMAP.rst
odoo/addons/stock_move_line_multi_company_security/readme/USAGE.rst
odoo/addons/stock_move_line_multi_company_security/security/stock_security.xml
odoo/addons/stock_move_line_multi_company_security/static/description/icon.png
odoo/addons/stock_move_line_multi_company_security/static/description/index.html
odoo/addons/stock_move_line_multi_company_security/tests/__init__.py
odoo/addons/stock_move_line_multi_company_security/tests/test_stock_move_line_multi_company_security.py
odoo12_addon_stock_move_line_multi_company_security-12.0.1.0.1.dist-info/METADATA
odoo12_addon_stock_move_line_multi_company_security-12.0.1.0.1.dist-info/RECORD
odoo12_addon_stock_move_line_multi_company_security-12.0.1.0.1.dist-info/WHEEL
odoo12_addon_stock_move_line_multi_company_security-12.0.1.0.1.dist-info/top_level.txt
